{"stats":{"minecraft:mined":{"cobalt_wireless:cobaltdeepslateore":2,"cobalt_wireless:cobaltore":7,"cobalt_wireless:cobaltblock":9},"minecraft:custom":{"minecraft:time_since_rest":11599,"minecraft:play_time":11599,"minecraft:walk_one_cm":22287,"minecraft:jump":7,"minecraft:leave_game":4,"minecraft:time_since_death":11599,"minecraft:total_world_time":11742,"minecraft:fly_one_cm":3831,"minecraft:fall_one_cm":211},"minecraft:used":{"cobalt_wireless:cobaltblock":18,"cobalt_wireless:cobaltore":10,"minecraft:piston":4,"minecraft:lever":1,"cobalt_wireless:cobaltdeepslateore":3,"minecraft:redstone":1,"cobalt_wireless:cobaltdustblock":1,"minecraft:stone_pickaxe":5,"minecraft:iron_pickaxe":18,"cobalt_wireless:cobaltblockwirelessoff":8,"cobalt_wireless:cobaltblocksignal":6,"cobalt_wireless:cobaltwrench":64},"minecraft:picked_up":{"cobalt_wireless:cobaltshard":18,"cobalt_wireless:cobaltblock":9}},"DataVersion":3465}